{
  "resourceType": "StructureDefinition",
  "id": "mii-pr-studie-studieneinschluss-anfrage",
  "url": "https://www.medizininformatik-initiative.de/fhir/modul-studie/StructureDefinition/mii-pr-studie-studieneinschluss-anfrage",
  "name": "MII_PR_Studie_Studieneinschluss_Anfrage",
  "title": "MII PR Studie Studieneinschluss Anfrage",
  "status": "active",
  "description": "Anfrage zum Studieneinschluss",
  "fhirVersion": "4.0.1",
  "kind": "resource",
  "abstract": false,
  "type": "ServiceRequest",
  "baseDefinition": "http://hl7.org/fhir/StructureDefinition/ServiceRequest",
  "derivation": "constraint",
  "differential": {
    "element": [
      {
        "id": "ServiceRequest.status",
        "path": "ServiceRequest.status",
        "mustSupport": true
      },
      {
        "id": "ServiceRequest.intent",
        "path": "ServiceRequest.intent",
        "patternCode": "proposal",
        "mustSupport": true
      },
      {
        "id": "ServiceRequest.category",
        "path": "ServiceRequest.category",
        "min": 1,
        "patternCodeableConcept": {
          "coding": [
            {
              "code": "110465008",
              "system": "http://snomed.info/sct",
              "display": "Clinical trial (procedure)"
            }
          ]
        },
        "mustSupport": true
      },
      {
        "id": "ServiceRequest.code",
        "path": "ServiceRequest.code",
        "min": 1,
        "patternCodeableConcept": {
          "coding": [
            {
              "code": "702475000",
              "system": "http://snomed.info/sct",
              "display": "Referral to clinical trial (procedure)"
            }
          ]
        },
        "mustSupport": true
      },
      {
        "id": "ServiceRequest.subject",
        "path": "ServiceRequest.subject",
        "type": [
          {
            "code": "Reference",
            "targetProfile": [
              "http://hl7.org/fhir/StructureDefinition/Patient"
            ]
          }
        ],
        "mustSupport": true
      },
      {
        "id": "ServiceRequest.supportingInfo",
        "path": "ServiceRequest.supportingInfo",
        "slicing": {
          "discriminator": [
            {
              "type": "profile",
              "path": "$this.resolve()"
            }
          ],
          "rules": "open"
        },
        "mustSupport": true
      },
      {
        "id": "ServiceRequest.supportingInfo:Studie",
        "path": "ServiceRequest.supportingInfo",
        "sliceName": "Studie",
        "min": 0,
        "max": "*",
        "type": [
          {
            "code": "Reference",
            "targetProfile": [
              "https://www.medizininformatik-initiative.de/fhir/modul-studie/StructureDefinition/mii-pr-studie-studie",
              "http://hl7.org/fhir/StructureDefinition/ResearchStudy"
            ]
          }
        ],
        "mustSupport": true
      },
      {
        "id": "ServiceRequest.supportingInfo:Proband",
        "path": "ServiceRequest.supportingInfo",
        "sliceName": "Proband",
        "min": 0,
        "max": "1",
        "type": [
          {
            "code": "Reference",
            "targetProfile": [
              "https://www.medizininformatik-initiative.de/fhir/modul-studie/StructureDefinition/mii-pr-studie-proband",
              "http://hl7.org/fhir/StructureDefinition/ResearchSubject"
            ]
          }
        ],
        "mustSupport": true
      }
    ]
  }
}
